AUTHORS.rst
CONTRIBUTING.rst
HISTORY.rst
LICENSE
MANIFEST.in
README.md
setup.cfg
setup.py
djcms_blog_plugin/__init__.py
djcms_blog_plugin/cms_plugins.py
djcms_blog_plugin/forms.py
djcms_blog_plugin/models.py
djcms_blog_plugin.egg-info/PKG-INFO
djcms_blog_plugin.egg-info/SOURCES.txt
djcms_blog_plugin.egg-info/dependency_links.txt
djcms_blog_plugin.egg-info/not-zip-safe
djcms_blog_plugin.egg-info/requires.txt
djcms_blog_plugin.egg-info/top_level.txt
djcms_blog_plugin/templates/djcms_blog_plugin/simple_blog_entries.html
docs/Makefile
docs/authors.rst
docs/conf.py
docs/contributing.rst
docs/history.rst
docs/index.rst
docs/installation.rst
docs/make.bat
docs/readme.rst
docs/usage.rst
tests/__init__.py
tests/requirements.txt
tests/settings.py
tests/test_cms_plugins.py
tests/test_models.py