Metadata-Version: 1.1
Name: djcms-blog-plugin
Version: 0.1.3
Summary: DjangoCMS Blog plugin
Home-page: https://github.com/carlosmart626/djcms_blog_plugin
Author: Carlos Martinez
Author-email: me@carlosmart.co
License: MIT license
Keywords: djcms_blog_plugin
Platform: UNKNOWN
Classifier: Development Status :: 2 - Pre-Alpha
Classifier: Intended Audience :: Developers
Classifier: License :: OSI Approved :: MIT License
Classifier: Natural Language :: English
Classifier: Programming Language :: Python :: 2
Classifier: Programming Language :: Python :: 2.7
Classifier: Programming Language :: Python :: 3
Classifier: Programming Language :: Python :: 3.4
Classifier: Programming Language :: Python :: 3.5
Classifier: Programming Language :: Python :: 3.6
Classifier: Programming Language :: Python :: 3.7
